[
    {
        "Bleu_1": 0.1354,
        "Bleu_2": 0.0514,
        "Bleu_3": 0.0214,
        "Bleu_4": 0.0094,
        "METEOR": 0.0931,
        "ROUGE_L": 0.0992,
        "CIDEr": 0.0035,
        "rouge1": 0.1743,
        "rouge2": 0.0255,
        "rougeL": 0.0974,
        "rougeLsum": 0.1138,
        "bleu": 0.0131,
        "ppl_pred": 139.26647440600468,
        "ppl_gt": 25.73515174367233,
        "method": "llava_recipe_onlyimage.json"
    },
    {
        "Bleu_1": 0.2756,
        "Bleu_2": 0.1436,
        "Bleu_3": 0.0782,
        "Bleu_4": 0.0444,
        "METEOR": 0.1873,
        "ROUGE_L": 0.1796,
        "CIDEr": 0.0356,
        "rouge1": 0.3485,
        "rouge2": 0.0946,
        "rougeL": 0.1754,
        "rougeLsum": 0.1954,
        "bleu": 0.0538,
        "ppl_pred": 10.518995959066887,
        "ppl_gt": 25.744144314340684,
        "method": "llava_recipe_ImageIng.json"
    },
    {
        "Bleu_1": 0.2913,
        "Bleu_2": 0.156,
        "Bleu_3": 0.0872,
        "Bleu_4": 0.0509,
        "METEOR": 0.1999,
        "ROUGE_L": 0.1879,
        "CIDEr": 0.044,
        "rouge1": 0.3668,
        "rouge2": 0.1062,
        "rougeL": 0.1833,
        "rougeLsum": 0.2037,
        "bleu": 0.0605,
        "ppl_pred": 10.92210565662384,
        "ppl_gt": 25.68670983314514,
        "method": "llava_recipe_noimage.json"
    },
    {
        "Bleu_1": 0.149,
        "Bleu_2": 0.057,
        "Bleu_3": 0.0238,
        "Bleu_4": 0.0104,
        "METEOR": 0.1023,
        "ROUGE_L": 0.1091,
        "CIDEr": 0.005,
        "rouge1": 0.1921,
        "rouge2": 0.0283,
        "rougeL": 0.1063,
        "rougeLsum": 0.1248,
        "bleu": 0.0145,
        "ppl_pred": 107.58723556899255,
        "ppl_gt": 25.74057657728272,
        "method": "llava_recipe_ImageTitle.json"
    },
    {
        "Bleu_1": 0.1926,
        "Bleu_2": 0.0909,
        "Bleu_3": 0.0459,
        "Bleu_4": 0.0242,
        "METEOR": 0.1397,
        "ROUGE_L": 0.1353,
        "CIDEr": 0.0173,
        "rouge1": 0.2562,
        "rouge2": 0.0576,
        "rougeL": 0.1325,
        "rougeLsum": 0.1627,
        "bleu": 0.0275,
        "ppl_pred": 26.826785805463793,
        "ppl_gt": 25.68670983314514,
        "method": "llava_recipe_onlyTitle.json"
    },
    {
        "Bleu_1": 0.2893,
        "Bleu_2": 0.154,
        "Bleu_3": 0.0865,
        "Bleu_4": 0.0505,
        "METEOR": 0.1995,
        "ROUGE_L": 0.1886,
        "CIDEr": 0.0409,
        "rouge1": 0.3663,
        "rouge2": 0.1047,
        "rougeL": 0.1833,
        "rougeLsum": 0.2033,
        "bleu": 0.0595,
        "ppl_pred": 11.123958384156227,
        "ppl_gt": 25.6867098736763,
        "method": "llava_recipe1k.json"
    }
]